CHANGES.rst
LICENSE
MANIFEST.in
README.md
pyproject.toml
setup.cfg
pptreport/__init__.py
pptreport/_version.py
pptreport/box.py
pptreport/cli.py
pptreport/config.py
pptreport/powerpointreport.py
pptreport/slide.py
pptreport.egg-info/PKG-INFO
pptreport.egg-info/SOURCES.txt
pptreport.egg-info/dependency_links.txt
pptreport.egg-info/entry_points.txt
pptreport.egg-info/requires.txt
pptreport.egg-info/top_level.txt
pptreport/fonts/OFL.txt
pptreport/fonts/OpenSans-Bold.ttf
pptreport/fonts/OpenSans-Italic.ttf
pptreport/fonts/OpenSans-Regular.ttf
tests/test_box.py
tests/test_classes.py
tests/test_cli.py
tests/test_input.py
tests/test_slide.py