Metadata-Version: 2.4
Name: pptreport
Version: 1.1.2
Home-page: https://github.com/loosolab/pptreport
Author: Mette Bentsen
Author-email: mette.bentsen@mpi-bn.mpg.de
License: MIT
Platform: Linux
Platform: Mac OS X
Platform: Windows
Classifier: Intended Audience :: Science/Research
Classifier: License :: OSI Approved :: MIT License
Classifier: Topic :: Scientific/Engineering :: Visualization
Classifier: Programming Language :: Python :: 3
Requires-Python: >=3
License-File: LICENSE
Requires-Dist: numpy
Requires-Dist: python-pptx>=0.6.23
Requires-Dist: pymupdf
Requires-Dist: natsort
Requires-Dist: mistune<3,>=2
Requires-Dist: importlib_resources
Dynamic: license-file
